MANIFEST.in
README.md
setup.py
bin/seu-cat
bin/seu-countdataset
bin/seu-du
bin/seu-install-completion
bin/seu-ls
bin/seu-mkdir
bin/seu-nentries
bin/seu-printbranches
bin/seu-rm
bin/seu-root-count
bin/seu-root-ls
bin/seu-version
seutils/__init__.py
seutils/cache.py
seutils/cli.py
seutils/completion.py
seutils/eos.py
seutils/fakefs.py
seutils/gfal_implementation.py
seutils/local_implementation.py
seutils/path.py
seutils/pyroot.py
seutils/pyxrd_implementation.py
seutils/root.py
seutils/root_cli.py
seutils/ssh.py
seutils/uproot_implementation.py
seutils/xrd_implementation.py
seutils.egg-info/PKG-INFO
seutils.egg-info/SOURCES.txt
seutils.egg-info/dependency_links.txt
seutils.egg-info/not-zip-safe
seutils.egg-info/top_level.txt
seutils/include/VERSION
test/test_cli.py
test/test_completion.py
test/test_fakefs.py
test/test_implementations.py
test/test_integration.py
test/test_path.py
test/test_root.py
test/test_root_cli.py
test/test_run_command.py