Metadata-Version: 1.0
Name: seutils
Version: 1.16
Summary: Description text
Home-page: https://github.com/tklijnsma/seutils.git
Author: Thomas Klijnsma
Author-email: tklijnsm@gmail.com
License: BSD 3-Clause License
Platform: UNKNOWN
